{
    "instance_name": "Rifki-2",
    "routes": [
        [11, 15, 5, 7, 1, 19, 9],
        [3, 18, 10, 2],
        [17, 14, 13, 8, 12, 6],
        [16, 4, 20]
    ],
    "cost": 7377.999999999998,
    "metadata": {
        "source": "kayros 0.2.0.dev0 TD-ACO (seed=1010, time_limit=120.0s)",
        "validated_by": "mamut-routing-lib td Duration checker",
        "route_durations": [2151.0, 2002.0, 2066.999999999998, 1158.0],
        "route_departure_times": [17538.0, 24864.0, 11607.000000000002, 37972.0],
        "authors": "Florian Rascoussier (0nyr)",
        "validated_cost": 7377.999999999998,
        "validated_num_routes": 4,
        "date": "2026-07-06T05:08:29",
        "optimality": {
            "proven": true,
            "prover": "kayros lera branch-price-and-cut (HiGHS backend; branch m5.9-exact-stepwise-labeling, commit 7f5f357)",
            "certificate": "Optimal under checker-exact route costs and standard LP/pricing tolerances. Certified by four independent solves (cold and warm starts x asymmetric and symmetric labeling modes) agreeing on the value, each with an audited exact-pricing phase and zero checker-infeasible priced columns.",
            "date": "2026-07-10",
            "arithmetic": "checker-exact route costs (IEEE-754 doubles, canonical route order); the proven optimum equals compute_solution_cost of the stored routes bit-exactly",
            "proven_optimum": 7377.999999999998,
            "dual_bound": 7377.999999999998,
            "wall_time_s": 38.8,
            "time_limit_s": 600.0,
            "checker": "mamut-routing-lib td Duration checker",
            "campaign": "2026-07-10 full TD re-certification on Grid'5000 (reservation 6763721 + retry 6765373)"
        }
    },
    "objective_function": "Duration"
}
