{
    "instance_name": "Rifki-19",
    "routes": [
        [39, 1, 42, 25, 19],
        [23, 32, 3, 46, 14, 27, 40, 41],
        [8, 6, 34, 24],
        [38, 43, 13, 47, 10, 21],
        [36, 7, 12, 50, 48, 18],
        [20, 15, 11, 30, 2, 4, 28, 29],
        [9, 5, 17, 26, 44, 35],
        [16, 37, 45, 22, 49, 31, 33]
    ],
    "cost": 17420.999999999993,
    "metadata": {
        "source": "kayros 0.2.0.dev0 TD-ACO (seed=1010, time_limit=300.0s)",
        "validated_by": "mamut-routing-lib td Duration checker",
        "route_durations": [1603.0000000000018, 2593.0, 1702.0, 1805.0, 2466.0, 2791.9999999999964, 1430.9999999999964, 3029.0],
        "route_departure_times": [15777.999999999998, 7518.0, 20160.0, 22955.0, 24811.0, 23760.000000000004, 28358.0, 36154.0],
        "authors": "Florian Rascoussier (0nyr)",
        "validated_cost": 17420.999999999993,
        "validated_num_routes": 8,
        "date": "2026-07-06T05:08:41"
    },
    "objective_function": "Duration"
}
