{
    "instance_name": "Rifki-3",
    "routes": [
        [11, 46, 10, 3, 26, 24, 37],
        [17, 21, 7, 43, 23, 44],
        [22, 8, 33, 36, 35, 48, 5],
        [25, 32, 14, 45, 47],
        [27, 12, 4, 41, 15],
        [30, 20, 18, 28, 50, 29, 39, 1, 6],
        [38, 19, 16, 42, 40, 9, 31, 2],
        [49, 13, 34]
    ],
    "cost": 15246.999999999989,
    "metadata": {
        "authors": "Florian Rascoussier (0nyr)",
        "source": "kayros 0.4.0.dev0 TD-ILS (seed=456, time_limit=300.0s)",
        "validated_by": "mamut-routing-lib td Duration checker",
        "date": "2026-07-08T03:22:58",
        "route_durations": [1927.9999999999964, 1519.0, 2190.0, 1499.0, 1683.9999999999964, 3213.9999999999964, 2245.0, 968.0],
        "route_departure_times": [28458.000000000004, 7200.0, 37676.0, 19250.0, 22320.000000000004, 23970.000000000004, 7206.0, 24480.0],
        "validated_cost": 15246.999999999989,
        "validated_num_routes": 8
    },
    "objective_function": "Duration"
}
